volosti_server_common/__init__.py
volosti_server_common/alembic.ini
volosti_server_common/migrations/README
volosti_server_common/migrations/env.py
volosti_server_common/migrations/script.py.mako
volosti_server_common/models/__init__.py
volosti_server_common/models/base.py
volosti_server_common/paths.py
volosti_server_common/py.typed
volosti_server_common/static/base.css
volosti_server_common/templates/base/base.jinja2
volosti_server_common-0.1.dev1.dist-info/LICENSE
volosti_server_common-0.1.dev1.dist-info/WHEEL
volosti_server_common-0.1.dev1.dist-info/METADATA
volosti_server_common-0.1.dev1.dist-info/RECORD
